lsquery/__init__.py
lsquery/__main__.py
lsquery/api.py
lsquery/config.py
lsquery/query.py
lsquery/server.py
lsquery/web_socket.py
lsquery-0.1.7.dist-info/LICENCE
lsquery-0.1.7.dist-info/METADATA
lsquery-0.1.7.dist-info/WHEEL
lsquery-0.1.7.dist-info/top_level.txt
lsquery-0.1.7.dist-info/RECORD
