Metadata-Version: 2.1
Name: lsquery
Version: 0.1.7
Summary: The project is used to spin up docker game servers
Home-page: https://lanslide.com.au
Author: Brendon Taylor
Author-email: nuke@lanslide.com.au
License: GNU GPL
License-File: LICENCE
Requires-Dist: asyncio ==3.4.3
Requires-Dist: docker ==6.1.3
Requires-Dist: opengsq ==1.4.3
Requires-Dist: python-decouple ==3.6
Requires-Dist: pytz ==2022.6
Requires-Dist: rcon ==2.1.1
Requires-Dist: websocket-client ==1.4.2
Requires-Dist: websockets ==10.4
